{
  "resourceType": "ClinicalUseDefinition",
  "id": "cysteine-idiopathic-bronchiectasis",
  "type": "indication",
  "status": "active",
  "subject": [
    {
      "reference": "MedicationKnowledge/cysteine"
    }
  ],
  "indication": {
    "diseaseSymptomProcedure": {
      "concept": {
        "text": "idiopathic bronchiectasis"
      }
    }
  },
  "extension": [
    {
      "url": "https://ustxgnn.yao.care/fhir/StructureDefinition/evidence-level",
      "valueCode": "L5"
    },
    {
      "url": "https://ustxgnn.yao.care/fhir/StructureDefinition/source",
      "valueString": "TxGNN Knowledge Graph"
    }
  ]
}